setup.cfg
setup.py
easymirror/__init__.py
easymirror/_vnpy.py
easymirror/api.py
easymirror/canine.py
easymirror/dealutils.py
easymirror/log.py
easymirror/mirror.py
easymirror/timestampecache.py
easymirror/vnpy.py
easymirror.egg-info/PKG-INFO
easymirror.egg-info/SOURCES.txt
easymirror.egg-info/dependency_links.txt
easymirror.egg-info/requires.txt
easymirror.egg-info/top_level.txt