Metadata-Version: 1.1
Name: easymirror
Version: 0.0.5
Summary: Rsync financial datasource.
Home-page: https://github.com/lamter/easymirror
Author: lamter
Author-email: lamter.fu@gmail.com
License: GPL
Keywords: Finance easy futures makeup
Platform: UNKNOWN
Classifier: Programming Language :: Python :: 2.7
Classifier: Programming Language :: Python :: 3.4
Classifier: Programming Language :: Python :: 3.5
